README.rst
setup.cfg
setup.py
tests/__init__.py
tests/test_theTVDB.py
thetvdb_api/Logger.py
thetvdb_api/__init__.py
thetvdb_api/api.py
thetvdb_api/cache.py
thetvdb_api/conf.py
thetvdb_api/theTVDB.py
thetvdb_api/theTVDBError.py
thetvdb_api/utils.py
thetvdb_api.egg-info/PKG-INFO
thetvdb_api.egg-info/SOURCES.txt
thetvdb_api.egg-info/dependency_links.txt
thetvdb_api.egg-info/not-zip-safe
thetvdb_api.egg-info/top_level.txt